myz_tools/__init__.py
myz_tools/all_test.py
myz_tools/common_maths.py
myz_tools/plotting_function_calls.py
myz_tools/source2md.py
myz_tools-0.2.5.data/data/requirements.txt
myz_tools-0.2.5.dist-info/LICENSE
myz_tools-0.2.5.dist-info/METADATA
myz_tools-0.2.5.dist-info/WHEEL
myz_tools-0.2.5.dist-info/top_level.txt
myz_tools-0.2.5.dist-info/RECORD
