Metadata-Version: 2.1
Name: myz-tools
Version: 0.2.5
Summary: Python helper tools
Home-page: https://pypi.org/project/myz_tools/
Author: 宇千思
Author-email: 
Classifier: License :: OSI Approved :: Apache Software License
Requires-Python: >=3.6
License-File: LICENSE
Requires-Dist: aiocontextvars==0.2.2
Requires-Dist: alabaster==0.7.16
Requires-Dist: anyio==4.4.0
Requires-Dist: argon2-cffi==23.1.0
Requires-Dist: argon2-cffi-bindings==21.2.0
Requires-Dist: arrow==1.3.0
Requires-Dist: astroid==3.2.4
Requires-Dist: asttokens==2.4.1
Requires-Dist: async-lru==2.0.4
Requires-Dist: atomicwrites==1.4.1
Requires-Dist: attrs==25.1.0
Requires-Dist: babel==2.16.0
Requires-Dist: beautifulsoup4==4.12.3
Requires-Dist: binary==1.0.0
Requires-Dist: bleach==6.2.0
Requires-Dist: bs4==0.0.2
Requires-Dist: cachetools==5.5.0
Requires-Dist: certifi==2024.7.4
Requires-Dist: cffi==1.17.1
Requires-Dist: chardet==5.2.0
Requires-Dist: charset-normalizer==3.3.2
Requires-Dist: click==8.1.7
Requires-Dist: colorama==0.4.6
Requires-Dist: comm==0.2.2
Requires-Dist: commonmark==0.9.1
Requires-Dist: contextvars==2.4
Requires-Dist: contourpy==1.2.1
Requires-Dist: cycler==0.12.1
Requires-Dist: DataProperty==1.0.1
Requires-Dist: debugpy==1.8.5
Requires-Dist: decorator==5.1.1
Requires-Dist: defusedxml==0.7.1
Requires-Dist: dill==0.3.8
Requires-Dist: distlib==0.3.8
Requires-Dist: docutils==0.21.2
Requires-Dist: dominate==2.9.1
Requires-Dist: et-xmlfile==2.0.0
Requires-Dist: exceptiongroup==1.2.2
Requires-Dist: executing==2.0.1
Requires-Dist: fastjsonschema==2.21.1
Requires-Dist: filelock==3.15.4
Requires-Dist: fonttools==4.53.1
Requires-Dist: fqdn==1.5.1
Requires-Dist: google-api-core==2.19.1
Requires-Dist: google-auth==2.34.0
Requires-Dist: google-cloud-bigquery==3.25.0
Requires-Dist: google-cloud-core==2.4.1
Requires-Dist: google-crc32c==1.5.0
Requires-Dist: google-resumable-media==2.7.2
Requires-Dist: googleapis-common-protos==1.63.2
Requires-Dist: graphviz==0.20.3
Requires-Dist: grpcio==1.65.5
Requires-Dist: grpcio-status==1.65.5
Requires-Dist: h11==0.14.0
Requires-Dist: httpcore==1.0.5
Requires-Dist: httpx==0.27.0
Requires-Dist: idna==3.7
Requires-Dist: imagesize==1.4.1
Requires-Dist: immutables==0.20
Requires-Dist: importlib-metadata==8.2.0
Requires-Dist: importlib-resources==6.4.3
Requires-Dist: ipykernel==6.29.5
Requires-Dist: ipython==8.18.1
Requires-Dist: ipywidgets==8.1.5
Requires-Dist: isoduration==20.11.0
Requires-Dist: isort==5.13.2
Requires-Dist: jedi==0.19.1
Requires-Dist: Jinja2==3.1.4
Requires-Dist: json5==0.10.0
Requires-Dist: jsonpickle==3.2.2
Requires-Dist: jsonpointer==3.0.0
Requires-Dist: jsonschema==4.23.0
Requires-Dist: jsonschema-specifications==2024.10.1
Requires-Dist: jupyter==1.1.1
Requires-Dist: jupyter-console==6.6.3
Requires-Dist: jupyter-events==0.12.0
Requires-Dist: jupyter-lsp==2.2.5
Requires-Dist: jupyter-client==8.6.2
Requires-Dist: jupyter-core==5.7.2
Requires-Dist: jupyter-server==2.15.0
Requires-Dist: jupyter-server-terminals==0.5.3
Requires-Dist: jupyterlab==4.3.5
Requires-Dist: jupyterlab-pygments==0.3.0
Requires-Dist: jupyterlab-server==2.27.3
Requires-Dist: jupyterlab-widgets==3.0.13
Requires-Dist: kiwisolver==1.4.5
Requires-Dist: loguru==0.5.3
Requires-Dist: MarkupSafe==2.1.5
Requires-Dist: matplotlib==3.9.2
Requires-Dist: matplotlib-inline==0.1.7
Requires-Dist: mbstrdecoder==1.1.3
Requires-Dist: mccabe==0.7.0
Requires-Dist: mistune==3.1.1
Requires-Dist: nbclient==0.10.2
Requires-Dist: nbconvert==7.16.6
Requires-Dist: nbformat==5.10.4
Requires-Dist: nest-asyncio==1.6.0
Requires-Dist: networkx==3.2.1
Requires-Dist: notebook==7.3.2
Requires-Dist: notebook-shim==0.2.4
Requires-Dist: numpy==2.0.1
Requires-Dist: openpyxl==3.1.5
Requires-Dist: overrides==7.7.0
Requires-Dist: packaging==24.1
Requires-Dist: pandas==2.2.2
Requires-Dist: pandocfilters==1.5.1
Requires-Dist: parso==0.8.4
Requires-Dist: pathvalidate==3.2.0
Requires-Dist: pbr==6.0.0
Requires-Dist: pillow==10.4.0
Requires-Dist: platformdirs==4.2.2
Requires-Dist: prettytable==3.11.0
Requires-Dist: prometheus-client==0.21.1
Requires-Dist: prompt-toolkit==3.0.47
Requires-Dist: proto-plus==1.24.0
Requires-Dist: protobuf==5.27.3
Requires-Dist: psutil==6.0.0
Requires-Dist: pure-eval==0.2.3
Requires-Dist: pyasn1==0.6.0
Requires-Dist: pyasn1-modules==0.4.0
Requires-Dist: pycallgraph5==0.1.0
Requires-Dist: pycparser==2.22
Requires-Dist: Pygments==2.18.0
Requires-Dist: pylint==3.2.6
Requires-Dist: pyparsing==3.1.2
Requires-Dist: pypinfo==21.0.0
Requires-Dist: pypistats==1.6.0
Requires-Dist: pytablewriter==1.2.0
Requires-Dist: python-call-graph==2.1.2
Requires-Dist: python-dateutil==2.9.0.post0
Requires-Dist: python-json-logger==3.2.1
Requires-Dist: python-slugify==8.0.4
Requires-Dist: pytz==2024.1
Requires-Dist: pyvis==0.1.9
Requires-Dist: pywin32==306
Requires-Dist: pywinpty==2.0.15
Requires-Dist: PyYAML==6.0.2
Requires-Dist: pyzmq==26.1.0
Requires-Dist: recommonmark==0.7.1
Requires-Dist: referencing==0.36.2
Requires-Dist: reportlab==4.2.2
Requires-Dist: requests==2.32.3
Requires-Dist: rfc3339-validator==0.1.4
Requires-Dist: rfc3986-validator==0.1.1
Requires-Dist: rpds-py==0.22.3
Requires-Dist: rsa==4.9
Requires-Dist: rst2pdf==0.102
Requires-Dist: Send2Trash==1.8.3
Requires-Dist: six==1.16.0
Requires-Dist: smartypants==2.0.1
Requires-Dist: sniffio==1.3.1
Requires-Dist: snowballstemmer==2.2.0
Requires-Dist: socksio==1.0.0
Requires-Dist: soupsieve==2.5
Requires-Dist: Sphinx==7.4.7
Requires-Dist: sphinxcontrib-applehelp==2.0.0
Requires-Dist: sphinxcontrib-devhelp==2.0.0
Requires-Dist: sphinxcontrib-htmlhelp==2.1.0
Requires-Dist: sphinxcontrib-jsmath==1.0.1
Requires-Dist: sphinxcontrib-qthelp==2.0.0
Requires-Dist: sphinxcontrib-serializinghtml==2.0.0
Requires-Dist: stack-data==0.6.3
Requires-Dist: stevedore==5.2.0
Requires-Dist: tabledata==1.3.3
Requires-Dist: tcolorpy==0.1.6
Requires-Dist: termcolor==2.4.0
Requires-Dist: terminado==0.18.1
Requires-Dist: text-unidecode==1.3
Requires-Dist: tinycss2==1.4.0
Requires-Dist: tinydb==4.8.0
Requires-Dist: tinyrecord==0.2.0
Requires-Dist: tomli==2.0.1
Requires-Dist: tomlkit==0.13.2
Requires-Dist: tornado==6.4.1
Requires-Dist: traitlets==5.14.3
Requires-Dist: typepy==1.3.2
Requires-Dist: types-python-dateutil==2.9.0.20241206
Requires-Dist: typing-extensions==4.12.2
Requires-Dist: tzdata==2024.1
Requires-Dist: uri-template==1.3.0
Requires-Dist: urllib3==2.2.2
Requires-Dist: virtualenv==20.26.3
Requires-Dist: virtualenv-clone==0.5.7
Requires-Dist: virtualenvwrapper==6.1.0
Requires-Dist: wcwidth==0.2.13
Requires-Dist: webcolors==24.11.1
Requires-Dist: webencodings==0.5.1
Requires-Dist: websocket-client==1.8.0
Requires-Dist: widgetsnbextension==4.0.13
Requires-Dist: win32-setctime==1.1.0
Requires-Dist: zipp==3.20.0
